quake/__init__.py
quake/example.py
indoquake-0.0.5.dist-info/LICENSE
indoquake-0.0.5.dist-info/METADATA
indoquake-0.0.5.dist-info/WHEEL
indoquake-0.0.5.dist-info/top_level.txt
indoquake-0.0.5.dist-info/RECORD
