Metadata-Version: 2.1
Name: indoquake
Version: 0.0.5
Summary: A Latest Earthquake Detection Package Taken Based on BMKG | Meteorological, Climatological, and Geophysical Agency
Author-email: Danang Firmanto <danangfirmino26@gmail.com>
Project-URL: Homepage, https://github.com/danangfir/indoquake
Project-URL: Bug Tracker, https://github.com/danangfir/indoquake/issues
Classifier: Programming Language :: Python :: 3
Classifier: License :: OSI Approved :: MIT License
Classifier: Operating System :: OS Independent
Requires-Python: >=3.7
License-File: LICENSE
